{
  "id": "service_detail_slice",
  "type": "SharedSlice",
  "name": "ServiceDetailSlice",
  "description": "ServiceDetailSlice",
  "variations": [
    {
      "id": "default",
      "name": "Default",
      "docURL": "...",
      "version": "initial",
      "description": "Default",
      "imageUrl": "",
      "primary": {
        "section_title": {
          "type": "Text",
          "config": {
            "label": "Section Title (Optional)",
            "placeholder": "Our Services"
          }
        }
      },
      "items": {
        "overtitle": {
          "type": "Text",
          "config": {
            "label": "Service Overtitle",
            "placeholder": "O NAŠOJ TVRTKI"
          }
        },
        "header": {
          "type": "StructuredText",
          "config": {
            "label": "Service Header",
            "placeholder": "Iskustvo, kvaliteta i odgovornost",
            "allowTargetBlank": true,
            "single": "heading1,heading2,heading3,heading4,heading5,heading6"
          }
        },
        "content": {
          "type": "StructuredText",
          "config": {
            "label": "Service Content",
            "placeholder": "Service description and details...",
            "allowTargetBlank": true,
            "multi": "paragraph,preformatted,heading4,heading5,heading6,strong,em,hyperlink,list-item,o-list-item"
          }
        },
        "image": {
          "type": "Image",
          "config": {
            "constraint": {},
            "thumbnails": [],
            "label": "Service Image"
          }
        }
      }
    }
  ]
}